{
  "annotations": {
    "list": [
      {
        "builtIn": 1,
        "datasource": {
          "type": "grafana",
          "uid": "-- Grafana --"
        },
        "enable": true,
        "hide": true,
        "iconColor": "rgba(0, 211, 255, 1)",
        "name": "Annotations & Alerts",
        "type": "dashboard"
      }
    ]
  },
  "description": "CRS (Code Reasoning State) activity, learning, persistence, and param extraction metrics. For session-level debugging, use Loki log search with session_id filter.",
  "editable": true,
  "fiscalYearStartMonth": 0,
  "graphTooltip": 1,
  "id": null,
  "links": [],
  "liveNow": false,
  "panels": [
    {
      "collapsed": false,
      "gridPos": { "h": 1, "w": 24, "x": 0, "y": 0 },
      "id": 100,
      "title": "CRS Activity Overview",
      "type": "row"
    },
    {
      "datasource": { "type": "prometheus", "uid": "prometheus" },
      "fieldConfig": {
        "defaults": {
          "color": { "mode": "palette-classic" },
          "custom": {
            "drawStyle": "bars",
            "fillOpacity": 80,
            "stacking": { "mode": "normal" }
          },
          "unit": "short"
        },
        "overrides": []
      },
      "gridPos": { "h": 8, "w": 12, "x": 0, "y": 1 },
      "id": 1,
      "options": {
        "legend": { "displayMode": "table", "placement": "bottom", "calcs": ["sum"] },
        "tooltip": { "mode": "multi" }
      },
      "targets": [
        {
          "datasource": { "type": "prometheus", "uid": "prometheus" },
          "expr": "sum by (activity, status) (increase(trace_crs_activities_total{activity=~\"$activity\"}[$__rate_interval]))",
          "legendFormat": "{{activity}} ({{status}})",
          "refId": "A"
        }
      ],
      "title": "CRS Activities by Type & Status",
      "type": "timeseries"
    },
    {
      "datasource": { "type": "prometheus", "uid": "prometheus" },
      "fieldConfig": {
        "defaults": {
          "color": { "mode": "palette-classic" },
          "custom": {
            "drawStyle": "line",
            "fillOpacity": 10
          },
          "unit": "s"
        },
        "overrides": []
      },
      "gridPos": { "h": 8, "w": 12, "x": 12, "y": 1 },
      "id": 2,
      "options": {
        "legend": { "displayMode": "table", "placement": "bottom", "calcs": ["mean", "max"] },
        "tooltip": { "mode": "multi" }
      },
      "targets": [
        {
          "datasource": { "type": "prometheus", "uid": "prometheus" },
          "expr": "histogram_quantile(0.50, sum by (le, activity) (rate(trace_crs_activity_duration_seconds_bucket{activity=~\"$activity\"}[$__rate_interval])))",
          "legendFormat": "p50 {{activity}}",
          "refId": "A"
        },
        {
          "datasource": { "type": "prometheus", "uid": "prometheus" },
          "expr": "histogram_quantile(0.95, sum by (le, activity) (rate(trace_crs_activity_duration_seconds_bucket{activity=~\"$activity\"}[$__rate_interval])))",
          "legendFormat": "p95 {{activity}}",
          "refId": "B"
        },
        {
          "datasource": { "type": "prometheus", "uid": "prometheus" },
          "expr": "histogram_quantile(0.99, sum by (le, activity) (rate(trace_crs_activity_duration_seconds_bucket{activity=~\"$activity\"}[$__rate_interval])))",
          "legendFormat": "p99 {{activity}}",
          "refId": "C"
        }
      ],
      "title": "Activity Duration p50/p95/p99",
      "type": "timeseries"
    },
    {
      "datasource": { "type": "prometheus", "uid": "prometheus" },
      "fieldConfig": {
        "defaults": {
          "color": { "mode": "value" },
          "mappings": [],
          "thresholds": {
            "mode": "absolute",
            "steps": [
              { "color": "green", "value": null },
              { "color": "yellow", "value": 50 },
              { "color": "red", "value": 100 }
            ]
          },
          "unit": "short"
        },
        "overrides": []
      },
      "gridPos": { "h": 4, "w": 6, "x": 0, "y": 9 },
      "id": 3,
      "options": {
        "colorMode": "value",
        "graphMode": "area",
        "justifyMode": "auto",
        "orientation": "auto",
        "reduceOptions": { "calcs": ["lastNotNull"], "fields": "", "values": false },
        "textMode": "auto"
      },
      "targets": [
        {
          "datasource": { "type": "prometheus", "uid": "prometheus" },
          "expr": "sum(increase(trace_crs_steps_recorded_total[$__rate_interval]))",
          "refId": "A"
        }
      ],
      "title": "Reasoning Steps Recorded",
      "type": "stat"
    },
    {
      "datasource": { "type": "prometheus", "uid": "prometheus" },
      "fieldConfig": {
        "defaults": {
          "color": { "mode": "value" },
          "mappings": [],
          "thresholds": {
            "mode": "absolute",
            "steps": [
              { "color": "blue", "value": null }
            ]
          },
          "unit": "short"
        },
        "overrides": []
      },
      "gridPos": { "h": 4, "w": 6, "x": 6, "y": 9 },
      "id": 4,
      "options": {
        "colorMode": "value",
        "graphMode": "area",
        "justifyMode": "auto",
        "orientation": "auto",
        "reduceOptions": { "calcs": ["lastNotNull"], "fields": "", "values": false },
        "textMode": "auto"
      },
      "targets": [
        {
          "datasource": { "type": "prometheus", "uid": "prometheus" },
          "expr": "crs_generation",
          "refId": "A"
        }
      ],
      "title": "Core CRS Generation",
      "type": "stat"
    },
    {
      "datasource": { "type": "prometheus", "uid": "prometheus" },
      "fieldConfig": {
        "defaults": {
          "color": { "mode": "value" },
          "mappings": [],
          "thresholds": {
            "mode": "absolute",
            "steps": [
              { "color": "green", "value": null },
              { "color": "orange", "value": 5 },
              { "color": "red", "value": 20 }
            ]
          },
          "unit": "short"
        },
        "overrides": []
      },
      "gridPos": { "h": 4, "w": 6, "x": 12, "y": 9 },
      "id": 5,
      "options": {
        "colorMode": "value",
        "graphMode": "area",
        "justifyMode": "auto",
        "orientation": "auto",
        "reduceOptions": { "calcs": ["lastNotNull"], "fields": "", "values": false },
        "textMode": "auto"
      },
      "targets": [
        {
          "datasource": { "type": "prometheus", "uid": "prometheus" },
          "expr": "sum(increase(trace_crs_conflicts_total[$__rate_interval]))",
          "refId": "A"
        }
      ],
      "title": "Delta Conflicts",
      "type": "stat"
    },
    {
      "datasource": { "type": "prometheus", "uid": "prometheus" },
      "fieldConfig": {
        "defaults": {
          "color": { "mode": "value" },
          "mappings": [],
          "thresholds": {
            "mode": "absolute",
            "steps": [
              { "color": "green", "value": null },
              { "color": "red", "value": 1 }
            ]
          },
          "unit": "short"
        },
        "overrides": []
      },
      "gridPos": { "h": 4, "w": 6, "x": 18, "y": 9 },
      "id": 6,
      "options": {
        "colorMode": "value",
        "graphMode": "area",
        "justifyMode": "auto",
        "orientation": "auto",
        "reduceOptions": { "calcs": ["lastNotNull"], "fields": "", "values": false },
        "textMode": "auto"
      },
      "targets": [
        {
          "datasource": { "type": "prometheus", "uid": "prometheus" },
          "expr": "sum(increase(trace_crs_recording_errors_total[$__rate_interval]))",
          "refId": "A"
        }
      ],
      "title": "Recording Errors",
      "type": "stat"
    },
    {
      "collapsed": false,
      "gridPos": { "h": 1, "w": 24, "x": 0, "y": 13 },
      "id": 200,
      "title": "Learning & Decisions",
      "type": "row"
    },
    {
      "datasource": { "type": "prometheus", "uid": "prometheus" },
      "fieldConfig": {
        "defaults": {
          "color": { "mode": "palette-classic" },
          "custom": {
            "drawStyle": "bars",
            "fillOpacity": 80,
            "stacking": { "mode": "normal" }
          },
          "unit": "short"
        },
        "overrides": []
      },
      "gridPos": { "h": 8, "w": 8, "x": 0, "y": 14 },
      "id": 7,
      "options": {
        "legend": { "displayMode": "table", "placement": "bottom", "calcs": ["sum"] },
        "tooltip": { "mode": "multi" }
      },
      "targets": [
        {
          "datasource": { "type": "prometheus", "uid": "prometheus" },
          "expr": "sum by (failure_type) (increase(trace_crs_clauses_learned_total[$__rate_interval]))",
          "legendFormat": "{{failure_type}}",
          "refId": "A"
        }
      ],
      "title": "Clauses Learned by Failure Type",
      "type": "timeseries"
    },
    {
      "datasource": { "type": "prometheus", "uid": "prometheus" },
      "fieldConfig": {
        "defaults": {
          "color": { "mode": "palette-classic" },
          "custom": { "align": "auto", "displayMode": "auto" },
          "unit": "short"
        },
        "overrides": []
      },
      "gridPos": { "h": 8, "w": 8, "x": 8, "y": 14 },
      "id": 8,
      "options": {
        "showHeader": true,
        "sortBy": [{ "desc": true, "displayName": "Value" }]
      },
      "targets": [
        {
          "datasource": { "type": "prometheus", "uid": "prometheus" },
          "expr": "topk(10, sum by (tool) (increase(trace_crs_decisions_blocked_total{tool=~\"$tool\"}[$__rate_interval])))",
          "format": "table",
          "instant": true,
          "legendFormat": "{{tool}}",
          "refId": "A"
        }
      ],
      "title": "Top Blocked Decisions by Tool",
      "type": "table",
      "transformations": [
        {
          "id": "organize",
          "options": {
            "excludeByName": { "Time": true },
            "renameByName": { "Value": "Blocked Count", "tool": "Tool" }
          }
        }
      ]
    },
    {
      "datasource": { "type": "prometheus", "uid": "prometheus" },
      "fieldConfig": {
        "defaults": {
          "color": { "mode": "palette-classic" },
          "custom": {
            "drawStyle": "bars",
            "fillOpacity": 80,
            "stacking": { "mode": "normal" }
          },
          "unit": "short"
        },
        "overrides": []
      },
      "gridPos": { "h": 8, "w": 8, "x": 16, "y": 14 },
      "id": 9,
      "options": {
        "legend": { "displayMode": "table", "placement": "bottom", "calcs": ["sum"] },
        "tooltip": { "mode": "multi" }
      },
      "targets": [
        {
          "datasource": { "type": "prometheus", "uid": "prometheus" },
          "expr": "sum by (algorithm) (increase(trace_crs_cycles_detected_total[$__rate_interval]))",
          "legendFormat": "{{algorithm}}",
          "refId": "A"
        }
      ],
      "title": "Cycles Detected by Algorithm",
      "type": "timeseries"
    },
    {
      "datasource": { "type": "prometheus", "uid": "prometheus" },
      "fieldConfig": {
        "defaults": {
          "color": { "mode": "palette-classic" },
          "custom": {
            "drawStyle": "bars",
            "fillOpacity": 60
          },
          "unit": "short"
        },
        "overrides": []
      },
      "gridPos": { "h": 8, "w": 12, "x": 0, "y": 22 },
      "id": 10,
      "options": {
        "legend": { "displayMode": "table", "placement": "bottom", "calcs": ["mean", "max"] },
        "tooltip": { "mode": "multi" }
      },
      "targets": [
        {
          "datasource": { "type": "prometheus", "uid": "prometheus" },
          "expr": "histogram_quantile(0.50, sum by (le, algorithm) (rate(trace_crs_cycle_length_bucket[$__rate_interval])))",
          "legendFormat": "p50 {{algorithm}}",
          "refId": "A"
        },
        {
          "datasource": { "type": "prometheus", "uid": "prometheus" },
          "expr": "histogram_quantile(0.95, sum by (le, algorithm) (rate(trace_crs_cycle_length_bucket[$__rate_interval])))",
          "legendFormat": "p95 {{algorithm}}",
          "refId": "B"
        }
      ],
      "title": "Cycle Length Distribution",
      "type": "timeseries"
    },
    {
      "datasource": { "type": "prometheus", "uid": "prometheus" },
      "fieldConfig": {
        "defaults": {
          "color": { "mode": "palette-classic" },
          "custom": {
            "drawStyle": "line",
            "fillOpacity": 10
          },
          "unit": "short"
        },
        "overrides": []
      },
      "gridPos": { "h": 8, "w": 12, "x": 12, "y": 22 },
      "id": 11,
      "options": {
        "legend": { "displayMode": "table", "placement": "bottom", "calcs": ["sum"] },
        "tooltip": { "mode": "multi" }
      },
      "targets": [
        {
          "datasource": { "type": "prometheus", "uid": "prometheus" },
          "expr": "sum by (type) (increase(trace_crs_constraints_added_total[$__rate_interval]))",
          "legendFormat": "{{type}}",
          "refId": "A"
        }
      ],
      "title": "Constraints Added by Type",
      "type": "timeseries"
    },
    {
      "collapsed": false,
      "gridPos": { "h": 1, "w": 24, "x": 0, "y": 30 },
      "id": 300,
      "title": "Proof Index",
      "type": "row"
    },
    {
      "datasource": { "type": "prometheus", "uid": "prometheus" },
      "fieldConfig": {
        "defaults": {
          "color": { "mode": "palette-classic" },
          "unit": "short"
        },
        "overrides": []
      },
      "gridPos": { "h": 8, "w": 8, "x": 0, "y": 31 },
      "id": 12,
      "options": {
        "displayLabels": ["percent"],
        "legend": { "displayMode": "table", "placement": "right", "calcs": ["sum"] },
        "pieType": "donut",
        "reduceOptions": { "calcs": ["sum"], "fields": "", "values": false },
        "tooltip": { "mode": "single" }
      },
      "targets": [
        {
          "datasource": { "type": "prometheus", "uid": "prometheus" },
          "expr": "sum by (status) (increase(trace_crs_proof_updates_total[$__rate_interval]))",
          "legendFormat": "{{status}}",
          "refId": "A"
        }
      ],
      "title": "Proof Updates by Status",
      "type": "piechart"
    },
    {
      "datasource": { "type": "prometheus", "uid": "prometheus" },
      "fieldConfig": {
        "defaults": {
          "color": { "mode": "scheme", "schemeName": "Oranges" },
          "custom": {
            "fillOpacity": 80,
            "scaleDistribution": { "type": "linear" }
          },
          "unit": "short"
        },
        "overrides": []
      },
      "gridPos": { "h": 8, "w": 8, "x": 8, "y": 31 },
      "id": 13,
      "options": {
        "calculate": true,
        "cellGap": 1,
        "color": { "mode": "scheme", "scheme": "Oranges" },
        "yAxis": { "axisLabel": "Activity" }
      },
      "targets": [
        {
          "datasource": { "type": "prometheus", "uid": "prometheus" },
          "expr": "sum by (activity) (increase(trace_crs_proof_updates_per_activity_bucket{activity=~\"$activity\"}[$__rate_interval]))",
          "legendFormat": "{{activity}}",
          "refId": "A"
        }
      ],
      "title": "Proof Updates per Activity (Heatmap)",
      "type": "heatmap"
    },
    {
      "datasource": { "type": "prometheus", "uid": "prometheus" },
      "fieldConfig": {
        "defaults": {
          "color": { "mode": "palette-classic" },
          "custom": {
            "drawStyle": "line",
            "fillOpacity": 10
          },
          "unit": "short"
        },
        "overrides": []
      },
      "gridPos": { "h": 8, "w": 8, "x": 16, "y": 31 },
      "id": 14,
      "options": {
        "legend": { "displayMode": "table", "placement": "bottom", "calcs": ["sum"] },
        "tooltip": { "mode": "multi" }
      },
      "targets": [
        {
          "datasource": { "type": "prometheus", "uid": "prometheus" },
          "expr": "sum(increase(trace_crs_dependencies_found_total[$__rate_interval]))",
          "legendFormat": "Dependencies Found",
          "refId": "A"
        }
      ],
      "title": "Dependencies Discovered",
      "type": "timeseries"
    },
    {
      "collapsed": false,
      "gridPos": { "h": 1, "w": 24, "x": 0, "y": 39 },
      "id": 400,
      "title": "Persistence Health",
      "type": "row"
    },
    {
      "datasource": { "type": "prometheus", "uid": "prometheus" },
      "fieldConfig": {
        "defaults": {
          "color": { "mode": "value" },
          "mappings": [],
          "thresholds": {
            "mode": "absolute",
            "steps": [
              { "color": "blue", "value": null }
            ]
          },
          "unit": "short"
        },
        "overrides": []
      },
      "gridPos": { "h": 4, "w": 4, "x": 0, "y": 40 },
      "id": 15,
      "options": {
        "colorMode": "value",
        "graphMode": "none",
        "justifyMode": "auto",
        "orientation": "auto",
        "reduceOptions": { "calcs": ["lastNotNull"], "fields": "", "values": false },
        "textMode": "auto"
      },
      "targets": [
        {
          "datasource": { "type": "prometheus", "uid": "prometheus" },
          "expr": "trace_crs_generation",
          "refId": "A"
        }
      ],
      "title": "Generation (Integration)",
      "type": "stat"
    },
    {
      "datasource": { "type": "prometheus", "uid": "prometheus" },
      "fieldConfig": {
        "defaults": {
          "color": { "mode": "palette-classic" },
          "custom": {
            "drawStyle": "bars",
            "fillOpacity": 80,
            "stacking": { "mode": "normal" }
          },
          "unit": "short"
        },
        "overrides": []
      },
      "gridPos": { "h": 8, "w": 10, "x": 4, "y": 40 },
      "id": 16,
      "options": {
        "legend": { "displayMode": "table", "placement": "bottom", "calcs": ["sum"] },
        "tooltip": { "mode": "multi" }
      },
      "targets": [
        {
          "datasource": { "type": "prometheus", "uid": "prometheus" },
          "expr": "sum by (operation, status) (increase(crs_backup_operations_total[$__rate_interval]))",
          "legendFormat": "{{operation}} ({{status}})",
          "refId": "A"
        }
      ],
      "title": "Backup Operations by Type & Status",
      "type": "timeseries"
    },
    {
      "datasource": { "type": "prometheus", "uid": "prometheus" },
      "fieldConfig": {
        "defaults": {
          "color": { "mode": "palette-classic" },
          "custom": {
            "drawStyle": "line",
            "fillOpacity": 10
          },
          "unit": "s"
        },
        "overrides": []
      },
      "gridPos": { "h": 8, "w": 10, "x": 14, "y": 40 },
      "id": 17,
      "options": {
        "legend": { "displayMode": "table", "placement": "bottom", "calcs": ["mean", "max"] },
        "tooltip": { "mode": "multi" }
      },
      "targets": [
        {
          "datasource": { "type": "prometheus", "uid": "prometheus" },
          "expr": "histogram_quantile(0.50, sum by (le) (rate(crs_backup_duration_seconds_bucket[$__rate_interval])))",
          "legendFormat": "Backup p50",
          "refId": "A"
        },
        {
          "datasource": { "type": "prometheus", "uid": "prometheus" },
          "expr": "histogram_quantile(0.95, sum by (le) (rate(crs_backup_duration_seconds_bucket[$__rate_interval])))",
          "legendFormat": "Backup p95",
          "refId": "B"
        },
        {
          "datasource": { "type": "prometheus", "uid": "prometheus" },
          "expr": "histogram_quantile(0.50, sum by (le) (rate(crs_restore_duration_seconds_bucket[$__rate_interval])))",
          "legendFormat": "Restore p50",
          "refId": "C"
        },
        {
          "datasource": { "type": "prometheus", "uid": "prometheus" },
          "expr": "histogram_quantile(0.95, sum by (le) (rate(crs_restore_duration_seconds_bucket[$__rate_interval])))",
          "legendFormat": "Restore p95",
          "refId": "D"
        }
      ],
      "title": "Backup/Restore Duration p50/p95",
      "type": "timeseries"
    },
    {
      "datasource": { "type": "prometheus", "uid": "prometheus" },
      "fieldConfig": {
        "defaults": {
          "color": { "mode": "value" },
          "mappings": [],
          "thresholds": {
            "mode": "absolute",
            "steps": [
              { "color": "green", "value": null },
              { "color": "yellow", "value": 1 },
              { "color": "red", "value": 5 }
            ]
          },
          "unit": "short"
        },
        "overrides": []
      },
      "gridPos": { "h": 4, "w": 4, "x": 0, "y": 48 },
      "id": 18,
      "options": {
        "colorMode": "value",
        "graphMode": "area",
        "justifyMode": "auto",
        "orientation": "auto",
        "reduceOptions": { "calcs": ["lastNotNull"], "fields": "", "values": false },
        "textMode": "auto"
      },
      "targets": [
        {
          "datasource": { "type": "prometheus", "uid": "prometheus" },
          "expr": "sum(increase(trace_crs_checkpoint_fallback_total[$__rate_interval]))",
          "refId": "A"
        }
      ],
      "title": "Checkpoint Fallbacks",
      "type": "stat"
    },
    {
      "datasource": { "type": "prometheus", "uid": "prometheus" },
      "fieldConfig": {
        "defaults": {
          "color": { "mode": "palette-classic" },
          "custom": {
            "drawStyle": "line",
            "fillOpacity": 10
          },
          "unit": "bytes"
        },
        "overrides": []
      },
      "gridPos": { "h": 4, "w": 10, "x": 4, "y": 48 },
      "id": 19,
      "options": {
        "legend": { "displayMode": "list", "placement": "bottom" },
        "tooltip": { "mode": "multi" }
      },
      "targets": [
        {
          "datasource": { "type": "prometheus", "uid": "prometheus" },
          "expr": "crs_backup_size_bytes",
          "legendFormat": "{{project_hash}}",
          "refId": "A"
        }
      ],
      "title": "Backup Size",
      "type": "timeseries"
    },
    {
      "datasource": { "type": "prometheus", "uid": "prometheus" },
      "fieldConfig": {
        "defaults": {
          "color": { "mode": "palette-classic" },
          "custom": {
            "drawStyle": "bars",
            "fillOpacity": 80,
            "stacking": { "mode": "normal" }
          },
          "unit": "short"
        },
        "overrides": []
      },
      "gridPos": { "h": 4, "w": 10, "x": 14, "y": 48 },
      "id": 20,
      "options": {
        "legend": { "displayMode": "list", "placement": "bottom" },
        "tooltip": { "mode": "multi" }
      },
      "targets": [
        {
          "datasource": { "type": "prometheus", "uid": "prometheus" },
          "expr": "sum by (error_type) (increase(trace_crs_recording_errors_total[$__rate_interval]))",
          "legendFormat": "{{error_type}}",
          "refId": "A"
        }
      ],
      "title": "Recording Errors by Type",
      "type": "timeseries"
    },
    {
      "collapsed": false,
      "gridPos": { "h": 1, "w": 24, "x": 0, "y": 52 },
      "id": 500,
      "title": "Session Restore",
      "type": "row"
    },
    {
      "datasource": { "type": "prometheus", "uid": "prometheus" },
      "fieldConfig": {
        "defaults": {
          "color": { "mode": "palette-classic" },
          "custom": {
            "drawStyle": "bars",
            "fillOpacity": 80,
            "stacking": { "mode": "normal" }
          },
          "unit": "short"
        },
        "overrides": []
      },
      "gridPos": { "h": 8, "w": 8, "x": 0, "y": 53 },
      "id": 21,
      "options": {
        "legend": { "displayMode": "table", "placement": "bottom", "calcs": ["sum"] },
        "tooltip": { "mode": "multi" }
      },
      "targets": [
        {
          "datasource": { "type": "prometheus", "uid": "prometheus" },
          "expr": "sum by (status) (increase(crs_session_restore_total[$__rate_interval]))",
          "legendFormat": "{{status}}",
          "refId": "A"
        }
      ],
      "title": "Session Restores by Status",
      "type": "timeseries"
    },
    {
      "datasource": { "type": "prometheus", "uid": "prometheus" },
      "fieldConfig": {
        "defaults": {
          "color": { "mode": "palette-classic" },
          "custom": {
            "drawStyle": "line",
            "fillOpacity": 10
          },
          "unit": "s"
        },
        "overrides": []
      },
      "gridPos": { "h": 8, "w": 8, "x": 8, "y": 53 },
      "id": 22,
      "options": {
        "legend": { "displayMode": "table", "placement": "bottom", "calcs": ["mean", "max"] },
        "tooltip": { "mode": "multi" }
      },
      "targets": [
        {
          "datasource": { "type": "prometheus", "uid": "prometheus" },
          "expr": "histogram_quantile(0.50, sum by (le) (rate(crs_session_restore_duration_seconds_bucket[$__rate_interval])))",
          "legendFormat": "Restore p50",
          "refId": "A"
        },
        {
          "datasource": { "type": "prometheus", "uid": "prometheus" },
          "expr": "histogram_quantile(0.95, sum by (le) (rate(crs_session_restore_duration_seconds_bucket[$__rate_interval])))",
          "legendFormat": "Restore p95",
          "refId": "B"
        }
      ],
      "title": "Session Restore Duration p50/p95",
      "type": "timeseries"
    },
    {
      "datasource": { "type": "prometheus", "uid": "prometheus" },
      "fieldConfig": {
        "defaults": {
          "color": { "mode": "palette-classic" },
          "custom": {
            "drawStyle": "line",
            "fillOpacity": 10
          },
          "unit": "s"
        },
        "overrides": []
      },
      "gridPos": { "h": 8, "w": 8, "x": 16, "y": 53 },
      "id": 23,
      "options": {
        "legend": { "displayMode": "list", "placement": "bottom" },
        "tooltip": { "mode": "multi" }
      },
      "targets": [
        {
          "datasource": { "type": "prometheus", "uid": "prometheus" },
          "expr": "crs_session_checkpoint_age_seconds",
          "legendFormat": "Checkpoint Age",
          "refId": "A"
        }
      ],
      "title": "Checkpoint Age",
      "type": "timeseries"
    },
    {
      "collapsed": false,
      "gridPos": { "h": 1, "w": 24, "x": 0, "y": 61 },
      "id": 600,
      "title": "Synthesis Quality & Symbol Resolution",
      "type": "row"
    },
    {
      "datasource": { "type": "prometheus", "uid": "prometheus" },
      "fieldConfig": {
        "defaults": {
          "color": { "mode": "palette-classic" },
          "custom": {
            "drawStyle": "bars",
            "fillOpacity": 60
          },
          "unit": "short"
        },
        "overrides": []
      },
      "gridPos": { "h": 8, "w": 12, "x": 0, "y": 62 },
      "id": 24,
      "options": {
        "legend": { "displayMode": "list", "placement": "bottom" },
        "tooltip": { "mode": "multi" }
      },
      "targets": [
        {
          "datasource": { "type": "prometheus", "uid": "prometheus" },
          "expr": "histogram_quantile(0.50, sum by (le) (rate(trace_synthesis_quality_score_bucket[$__rate_interval])))",
          "legendFormat": "p50",
          "refId": "A"
        },
        {
          "datasource": { "type": "prometheus", "uid": "prometheus" },
          "expr": "histogram_quantile(0.25, sum by (le) (rate(trace_synthesis_quality_score_bucket[$__rate_interval])))",
          "legendFormat": "p25",
          "refId": "B"
        },
        {
          "datasource": { "type": "prometheus", "uid": "prometheus" },
          "expr": "histogram_quantile(0.75, sum by (le) (rate(trace_synthesis_quality_score_bucket[$__rate_interval])))",
          "legendFormat": "p75",
          "refId": "C"
        }
      ],
      "title": "Synthesis Quality Score Distribution",
      "type": "timeseries"
    },
    {
      "datasource": { "type": "prometheus", "uid": "prometheus" },
      "fieldConfig": {
        "defaults": {
          "color": { "mode": "palette-classic" },
          "custom": {
            "drawStyle": "bars",
            "fillOpacity": 80,
            "stacking": { "mode": "normal" }
          },
          "unit": "short"
        },
        "overrides": []
      },
      "gridPos": { "h": 8, "w": 12, "x": 12, "y": 62 },
      "id": 25,
      "options": {
        "legend": { "displayMode": "table", "placement": "bottom", "calcs": ["sum"] },
        "tooltip": { "mode": "multi" }
      },
      "targets": [
        {
          "datasource": { "type": "prometheus", "uid": "prometheus" },
          "expr": "sum by (strategy) (increase(trace_symbol_resolution_attempts_total[$__rate_interval]))",
          "legendFormat": "{{strategy}}",
          "refId": "A"
        }
      ],
      "title": "Symbol Resolution Attempts by Strategy",
      "type": "timeseries"
    },
    {
      "datasource": { "type": "prometheus", "uid": "prometheus" },
      "fieldConfig": {
        "defaults": {
          "color": { "mode": "palette-classic" },
          "custom": {
            "drawStyle": "line",
            "fillOpacity": 10
          },
          "unit": "short"
        },
        "overrides": []
      },
      "gridPos": { "h": 8, "w": 12, "x": 0, "y": 70 },
      "id": 26,
      "options": {
        "legend": { "displayMode": "list", "placement": "bottom" },
        "tooltip": { "mode": "multi" }
      },
      "targets": [
        {
          "datasource": { "type": "prometheus", "uid": "prometheus" },
          "expr": "sum(increase(trace_symbol_cache_hits_total[$__rate_interval]))",
          "legendFormat": "Cache Hits",
          "refId": "A"
        },
        {
          "datasource": { "type": "prometheus", "uid": "prometheus" },
          "expr": "sum(increase(trace_symbol_cache_misses_total[$__rate_interval]))",
          "legendFormat": "Cache Misses",
          "refId": "B"
        }
      ],
      "title": "Symbol Cache Hit/Miss",
      "type": "timeseries"
    },
    {
      "datasource": { "type": "prometheus", "uid": "prometheus" },
      "fieldConfig": {
        "defaults": {
          "color": { "mode": "palette-classic" },
          "custom": {
            "drawStyle": "line",
            "fillOpacity": 10
          },
          "unit": "short"
        },
        "overrides": []
      },
      "gridPos": { "h": 8, "w": 12, "x": 12, "y": 70 },
      "id": 27,
      "options": {
        "legend": { "displayMode": "list", "placement": "bottom" },
        "tooltip": { "mode": "multi" }
      },
      "targets": [
        {
          "datasource": { "type": "prometheus", "uid": "prometheus" },
          "expr": "sum by (index) (crs_index_size)",
          "legendFormat": "{{index}}",
          "refId": "A"
        }
      ],
      "title": "CRS Index Sizes",
      "type": "timeseries"
    },
    {
      "collapsed": false,
      "gridPos": { "h": 1, "w": 24, "x": 0, "y": 78 },
      "id": 700,
      "title": "Dependency Index & Cache",
      "type": "row"
    },
    {
      "datasource": { "type": "prometheus", "uid": "prometheus" },
      "fieldConfig": {
        "defaults": {
          "color": { "mode": "palette-classic" },
          "custom": {
            "drawStyle": "line",
            "fillOpacity": 10
          },
          "unit": "s"
        },
        "overrides": []
      },
      "gridPos": { "h": 8, "w": 12, "x": 0, "y": 79 },
      "id": 28,
      "options": {
        "legend": { "displayMode": "table", "placement": "bottom", "calcs": ["mean", "max"] },
        "tooltip": { "mode": "multi" }
      },
      "targets": [
        {
          "datasource": { "type": "prometheus", "uid": "prometheus" },
          "expr": "histogram_quantile(0.50, sum by (le, operation) (rate(crs_dependency_index_query_duration_seconds_bucket[$__rate_interval])))",
          "legendFormat": "p50 {{operation}}",
          "refId": "A"
        },
        {
          "datasource": { "type": "prometheus", "uid": "prometheus" },
          "expr": "histogram_quantile(0.95, sum by (le, operation) (rate(crs_dependency_index_query_duration_seconds_bucket[$__rate_interval])))",
          "legendFormat": "p95 {{operation}}",
          "refId": "B"
        }
      ],
      "title": "Dependency Index Query Duration p50/p95",
      "type": "timeseries"
    },
    {
      "datasource": { "type": "prometheus", "uid": "prometheus" },
      "fieldConfig": {
        "defaults": {
          "color": { "mode": "palette-classic" },
          "custom": {
            "drawStyle": "line",
            "fillOpacity": 10
          },
          "unit": "short"
        },
        "overrides": []
      },
      "gridPos": { "h": 8, "w": 12, "x": 12, "y": 79 },
      "id": 29,
      "options": {
        "legend": { "displayMode": "list", "placement": "bottom" },
        "tooltip": { "mode": "multi" }
      },
      "targets": [
        {
          "datasource": { "type": "prometheus", "uid": "prometheus" },
          "expr": "sum(increase(crs_dependency_index_cache_hits_total[$__rate_interval]))",
          "legendFormat": "Cache Hits",
          "refId": "A"
        },
        {
          "datasource": { "type": "prometheus", "uid": "prometheus" },
          "expr": "sum(increase(crs_dependency_index_cache_misses_total[$__rate_interval]))",
          "legendFormat": "Cache Misses",
          "refId": "B"
        },
        {
          "datasource": { "type": "prometheus", "uid": "prometheus" },
          "expr": "sum(increase(crs_dependency_index_cache_invalidations_total[$__rate_interval]))",
          "legendFormat": "Invalidations",
          "refId": "C"
        }
      ],
      "title": "Dependency Index Cache",
      "type": "timeseries"
    },
    {
      "datasource": { "type": "prometheus", "uid": "prometheus" },
      "fieldConfig": {
        "defaults": {
          "color": { "mode": "value" },
          "mappings": [],
          "thresholds": {
            "mode": "absolute",
            "steps": [
              { "color": "blue", "value": null }
            ]
          },
          "unit": "short"
        },
        "overrides": []
      },
      "gridPos": { "h": 4, "w": 6, "x": 0, "y": 87 },
      "id": 30,
      "options": {
        "colorMode": "value",
        "graphMode": "area",
        "justifyMode": "auto",
        "orientation": "auto",
        "reduceOptions": { "calcs": ["lastNotNull"], "fields": "", "values": false },
        "textMode": "auto"
      },
      "targets": [
        {
          "datasource": { "type": "prometheus", "uid": "prometheus" },
          "expr": "crs_dependency_index_edge_count",
          "refId": "A"
        }
      ],
      "title": "Dependency Edge Count",
      "type": "stat"
    },
    {
      "collapsed": false,
      "gridPos": { "h": 1, "w": 24, "x": 0, "y": 91 },
      "id": 800,
      "title": "Param Extraction (CRS-14)",
      "type": "row"
    },
    {
      "datasource": { "type": "prometheus", "uid": "prometheus" },
      "fieldConfig": {
        "defaults": {
          "color": { "mode": "palette-classic" },
          "custom": {
            "drawStyle": "bars",
            "fillOpacity": 80,
            "stacking": { "mode": "normal" }
          },
          "unit": "short"
        },
        "overrides": []
      },
      "gridPos": { "h": 8, "w": 12, "x": 0, "y": 92 },
      "id": 31,
      "options": {
        "legend": { "displayMode": "table", "placement": "bottom", "calcs": ["sum"] },
        "tooltip": { "mode": "multi" }
      },
      "targets": [
        {
          "datasource": { "type": "prometheus", "uid": "prometheus" },
          "expr": "sum by (outcome) (increase(trace_param_extraction_speculative_total[$__rate_interval]))",
          "legendFormat": "{{outcome}}",
          "refId": "A"
        }
      ],
      "title": "Speculative Extraction Outcomes",
      "type": "timeseries"
    },
    {
      "datasource": { "type": "prometheus", "uid": "prometheus" },
      "fieldConfig": {
        "defaults": {
          "color": { "mode": "palette-classic" },
          "custom": {
            "drawStyle": "line",
            "fillOpacity": 10
          },
          "unit": "s"
        },
        "overrides": []
      },
      "gridPos": { "h": 8, "w": 12, "x": 12, "y": 92 },
      "id": 32,
      "options": {
        "legend": { "displayMode": "table", "placement": "bottom", "calcs": ["mean", "max"] },
        "tooltip": { "mode": "multi" }
      },
      "targets": [
        {
          "datasource": { "type": "prometheus", "uid": "prometheus" },
          "expr": "histogram_quantile(0.50, sum by (le, outcome) (rate(trace_param_extraction_speculative_duration_seconds_bucket[$__rate_interval])))",
          "legendFormat": "p50 {{outcome}}",
          "refId": "A"
        },
        {
          "datasource": { "type": "prometheus", "uid": "prometheus" },
          "expr": "histogram_quantile(0.95, sum by (le, outcome) (rate(trace_param_extraction_speculative_duration_seconds_bucket[$__rate_interval])))",
          "legendFormat": "p95 {{outcome}}",
          "refId": "B"
        }
      ],
      "title": "Speculative Extraction Duration by Outcome p50/p95",
      "type": "timeseries"
    },
    {
      "collapsed": false,
      "gridPos": { "h": 1, "w": 24, "x": 0, "y": 100 },
      "id": 900,
      "title": "NATS JetStream (CRS-27)",
      "type": "row"
    },
    {
      "datasource": { "type": "prometheus", "uid": "prometheus" },
      "fieldConfig": {
        "defaults": {
          "color": { "mode": "thresholds" },
          "thresholds": {
            "steps": [
              { "color": "green", "value": null },
              { "color": "yellow", "value": 50000 },
              { "color": "red", "value": 90000 }
            ]
          },
          "unit": "short"
        },
        "overrides": []
      },
      "gridPos": { "h": 4, "w": 8, "x": 0, "y": 101 },
      "id": 901,
      "options": {
        "reduceOptions": { "calcs": ["lastNotNull"] },
        "textMode": "auto",
        "colorMode": "value",
        "graphMode": "none"
      },
      "targets": [
        {
          "datasource": { "type": "prometheus", "uid": "prometheus" },
          "expr": "gnatsd_jetstream_stream_total_messages{stream=\"CRS_DELTAS\"}",
          "legendFormat": "Messages",
          "refId": "A"
        }
      ],
      "title": "NATS Stream Messages",
      "type": "stat"
    },
    {
      "datasource": { "type": "prometheus", "uid": "prometheus" },
      "fieldConfig": {
        "defaults": {
          "color": { "mode": "thresholds" },
          "thresholds": {
            "steps": [
              { "color": "green", "value": null },
              { "color": "yellow", "value": 104857600 },
              { "color": "red", "value": 536870912 }
            ]
          },
          "unit": "decbytes"
        },
        "overrides": []
      },
      "gridPos": { "h": 4, "w": 8, "x": 8, "y": 101 },
      "id": 902,
      "options": {
        "reduceOptions": { "calcs": ["lastNotNull"] },
        "textMode": "auto",
        "colorMode": "value",
        "graphMode": "none"
      },
      "targets": [
        {
          "datasource": { "type": "prometheus", "uid": "prometheus" },
          "expr": "gnatsd_jetstream_stream_total_bytes{stream=\"CRS_DELTAS\"}",
          "legendFormat": "Bytes",
          "refId": "A"
        }
      ],
      "title": "NATS Stream Size",
      "type": "stat"
    },
    {
      "datasource": { "type": "prometheus", "uid": "prometheus" },
      "fieldConfig": {
        "defaults": {
          "color": { "mode": "thresholds" },
          "thresholds": {
            "steps": [
              { "color": "green", "value": null },
              { "color": "red", "value": 1 }
            ]
          },
          "unit": "short"
        },
        "overrides": []
      },
      "gridPos": { "h": 4, "w": 8, "x": 16, "y": 101 },
      "id": 903,
      "options": {
        "reduceOptions": { "calcs": ["lastNotNull"] },
        "textMode": "auto",
        "colorMode": "value",
        "graphMode": "area"
      },
      "targets": [
        {
          "datasource": { "type": "prometheus", "uid": "prometheus" },
          "expr": "crs_nats_journal_corrupted_total",
          "legendFormat": "{{operation}}",
          "refId": "A"
        }
      ],
      "title": "CRC Corruption Count",
      "type": "stat"
    },
    {
      "datasource": { "type": "prometheus", "uid": "prometheus" },
      "fieldConfig": {
        "defaults": {
          "color": { "mode": "palette-classic" },
          "custom": {
            "drawStyle": "bars",
            "fillOpacity": 80,
            "stacking": { "mode": "normal" }
          },
          "unit": "short"
        },
        "overrides": []
      },
      "gridPos": { "h": 8, "w": 12, "x": 0, "y": 105 },
      "id": 904,
      "options": {
        "legend": { "displayMode": "table", "placement": "bottom", "calcs": ["sum"] },
        "tooltip": { "mode": "multi" }
      },
      "targets": [
        {
          "datasource": { "type": "prometheus", "uid": "prometheus" },
          "expr": "sum by (delta_type) (rate(crs_nats_journal_append_total{status=\"success\"}[$__rate_interval]))",
          "legendFormat": "{{delta_type}}",
          "refId": "A"
        }
      ],
      "title": "Delta Append Rate",
      "type": "timeseries"
    },
    {
      "datasource": { "type": "prometheus", "uid": "prometheus" },
      "fieldConfig": {
        "defaults": {
          "color": { "mode": "palette-classic" },
          "custom": {
            "drawStyle": "line",
            "fillOpacity": 10
          },
          "unit": "s"
        },
        "overrides": []
      },
      "gridPos": { "h": 8, "w": 12, "x": 12, "y": 105 },
      "id": 905,
      "options": {
        "legend": { "displayMode": "table", "placement": "bottom", "calcs": ["mean", "max"] },
        "tooltip": { "mode": "multi" }
      },
      "targets": [
        {
          "datasource": { "type": "prometheus", "uid": "prometheus" },
          "expr": "histogram_quantile(0.50, sum by (le) (rate(crs_nats_journal_append_duration_seconds_bucket{status=\"success\"}[$__rate_interval])))",
          "legendFormat": "p50",
          "refId": "A"
        },
        {
          "datasource": { "type": "prometheus", "uid": "prometheus" },
          "expr": "histogram_quantile(0.95, sum by (le) (rate(crs_nats_journal_append_duration_seconds_bucket{status=\"success\"}[$__rate_interval])))",
          "legendFormat": "p95",
          "refId": "B"
        },
        {
          "datasource": { "type": "prometheus", "uid": "prometheus" },
          "expr": "histogram_quantile(0.99, sum by (le) (rate(crs_nats_journal_append_duration_seconds_bucket{status=\"success\"}[$__rate_interval])))",
          "legendFormat": "p99",
          "refId": "C"
        }
      ],
      "title": "Append Latency p50/p95/p99",
      "type": "timeseries"
    },
    {
      "datasource": { "type": "prometheus", "uid": "prometheus" },
      "fieldConfig": {
        "defaults": {
          "color": { "mode": "palette-classic" },
          "custom": {
            "drawStyle": "line",
            "fillOpacity": 10
          },
          "unit": "short"
        },
        "overrides": []
      },
      "gridPos": { "h": 8, "w": 12, "x": 0, "y": 113 },
      "id": 906,
      "options": {
        "legend": { "displayMode": "table", "placement": "bottom", "calcs": ["sum", "mean"] },
        "tooltip": { "mode": "multi" }
      },
      "targets": [
        {
          "datasource": { "type": "prometheus", "uid": "prometheus" },
          "expr": "rate(crs_nats_journal_replay_total{status=\"success\"}[$__rate_interval])",
          "legendFormat": "replays/s",
          "refId": "A"
        },
        {
          "datasource": { "type": "prometheus", "uid": "prometheus" },
          "expr": "histogram_quantile(0.50, sum by (le) (rate(crs_nats_journal_replay_deltas_bucket[$__rate_interval])))",
          "legendFormat": "deltas/replay p50",
          "refId": "B"
        }
      ],
      "title": "Replay Operations",
      "type": "timeseries"
    },
    {
      "datasource": { "type": "prometheus", "uid": "prometheus" },
      "fieldConfig": {
        "defaults": {
          "color": { "mode": "palette-classic" },
          "custom": {
            "drawStyle": "line",
            "fillOpacity": 10
          },
          "unit": "short"
        },
        "overrides": []
      },
      "gridPos": { "h": 8, "w": 12, "x": 12, "y": 113 },
      "id": 907,
      "options": {
        "legend": { "displayMode": "table", "placement": "bottom", "calcs": ["sum"] },
        "tooltip": { "mode": "multi" }
      },
      "targets": [
        {
          "datasource": { "type": "prometheus", "uid": "prometheus" },
          "expr": "sum by (status) (rate(crs_nats_journal_checkpoint_total[$__rate_interval]))",
          "legendFormat": "{{status}}",
          "refId": "A"
        }
      ],
      "title": "Checkpoint Activity",
      "type": "timeseries"
    },
    {
      "datasource": { "type": "prometheus", "uid": "prometheus" },
      "fieldConfig": {
        "defaults": {
          "color": { "mode": "thresholds" },
          "mappings": [
            { "options": { "0": { "text": "Healthy", "color": "green" }, "1": { "text": "Degraded", "color": "red" } }, "type": "value" }
          ],
          "thresholds": {
            "steps": [
              { "color": "green", "value": null },
              { "color": "red", "value": 1 }
            ]
          }
        },
        "overrides": []
      },
      "gridPos": { "h": 4, "w": 8, "x": 0, "y": 121 },
      "id": 908,
      "options": {
        "reduceOptions": { "calcs": ["lastNotNull"] },
        "textMode": "auto",
        "colorMode": "background",
        "graphMode": "none"
      },
      "targets": [
        {
          "datasource": { "type": "prometheus", "uid": "prometheus" },
          "expr": "crs_nats_journal_degraded",
          "legendFormat": "NATS Status",
          "refId": "A"
        }
      ],
      "title": "Degraded Mode",
      "type": "stat"
    },
    {
      "datasource": { "type": "prometheus", "uid": "prometheus" },
      "fieldConfig": {
        "defaults": {
          "color": { "mode": "thresholds" },
          "thresholds": {
            "steps": [
              { "color": "blue", "value": null },
              { "color": "green", "value": 1 }
            ]
          },
          "unit": "short"
        },
        "overrides": []
      },
      "gridPos": { "h": 4, "w": 8, "x": 8, "y": 121 },
      "id": 909,
      "options": {
        "reduceOptions": { "calcs": ["lastNotNull"] },
        "textMode": "auto",
        "colorMode": "value",
        "graphMode": "area"
      },
      "targets": [
        {
          "datasource": { "type": "prometheus", "uid": "prometheus" },
          "expr": "crs_sse_connections_active",
          "legendFormat": "Active SSE",
          "refId": "A"
        }
      ],
      "title": "SSE Connections",
      "type": "stat"
    },
    {
      "datasource": { "type": "prometheus", "uid": "prometheus" },
      "fieldConfig": {
        "defaults": {
          "color": { "mode": "palette-classic" },
          "custom": {
            "drawStyle": "line",
            "fillOpacity": 10
          },
          "unit": "short"
        },
        "overrides": []
      },
      "gridPos": { "h": 4, "w": 8, "x": 16, "y": 121 },
      "id": 910,
      "options": {
        "legend": { "displayMode": "list", "placement": "bottom" },
        "tooltip": { "mode": "multi" }
      },
      "targets": [
        {
          "datasource": { "type": "prometheus", "uid": "prometheus" },
          "expr": "sum by (event_type) (rate(crs_sse_events_sent_total[$__rate_interval]))",
          "legendFormat": "{{event_type}}",
          "refId": "A"
        }
      ],
      "title": "SSE Event Throughput",
      "type": "timeseries"
    },
    {
      "datasource": { "type": "prometheus", "uid": "prometheus" },
      "fieldConfig": {
        "defaults": {
          "color": { "mode": "palette-classic" },
          "custom": {
            "drawStyle": "line",
            "fillOpacity": 10
          },
          "unit": "short"
        },
        "overrides": []
      },
      "gridPos": { "h": 8, "w": 24, "x": 0, "y": 125 },
      "id": 911,
      "options": {
        "legend": { "displayMode": "table", "placement": "bottom", "calcs": ["mean", "max"] },
        "tooltip": { "mode": "multi" }
      },
      "targets": [
        {
          "datasource": { "type": "prometheus", "uid": "prometheus" },
          "expr": "gnatsd_jetstream_consumer_num_pending",
          "legendFormat": "{{stream}} / {{consumer}}",
          "refId": "A"
        }
      ],
      "title": "Consumer Lag (Pending Messages)",
      "type": "timeseries"
    }
  ],
  "schemaVersion": 38,
  "style": "dark",
  "tags": ["crs", "aleutian", "trace"],
  "templating": {
    "list": [
      {
        "current": {
          "selected": false,
          "text": "All",
          "value": "$__all"
        },
        "datasource": { "type": "prometheus", "uid": "prometheus" },
        "definition": "label_values(trace_crs_activities_total, activity)",
        "hide": 0,
        "includeAll": true,
        "multi": true,
        "name": "activity",
        "options": [],
        "query": "label_values(trace_crs_activities_total, activity)",
        "refresh": 2,
        "regex": "",
        "sort": 1,
        "type": "query"
      },
      {
        "current": {
          "selected": false,
          "text": "All",
          "value": "$__all"
        },
        "datasource": { "type": "prometheus", "uid": "prometheus" },
        "definition": "label_values(trace_crs_decisions_blocked_total, tool)",
        "hide": 0,
        "includeAll": true,
        "multi": true,
        "name": "tool",
        "options": [],
        "query": "label_values(trace_crs_decisions_blocked_total, tool)",
        "refresh": 2,
        "regex": "",
        "sort": 1,
        "type": "query"
      }
    ]
  },
  "time": {
    "from": "now-1h",
    "to": "now"
  },
  "timepicker": {},
  "timezone": "",
  "title": "CRS - Code Reasoning State",
  "uid": "aleutian-crs",
  "version": 1
}
